{"title":"Web response times (1 month)","hits":0,"description":"","panelsJSON":"[{\"col\":1,\"id\":\"IIS_iQube_PUT_Translation_Verification_99pctl_Response_Time_1mo\",\"panelIndex\":1,\"row\":1,\"size_x\":6,\"size_y\":4,\"type\":\"visualization\"},{\"col\":7,\"id\":\"IIS_iQube_TC_Avg_Response_Time_1mo\",\"panelIndex\":3,\"row\":1,\"size_x\":6,\"size_y\":4,\"type\":\"visualization\"},{\"col\":1,\"id\":\"IIS_iQube_PUT_Translation_And_Verification_And_GET_Segment_Request_Count_1mo\",\"panelIndex\":4,\"size_x\":6,\"size_y\":4,\"row\":5,\"type\":\"visualization\"},{\"col\":7,\"id\":\"IIS_iQube_GET_Project_99pctl_Response_Time_1mo\",\"panelIndex\":5,\"size_x\":6,\"size_y\":4,\"row\":5,\"type\":\"visualization\"},{\"col\":1,\"id\":\"IIS_iQube_Failed_Request_Count_1mo\",\"panelIndex\":6,\"row\":9,\"size_x\":6,\"size_y\":4,\"type\":\"visualization\"}]","optionsJSON":"{\"darkTheme\":true}","uiStateJSON":"{}","version":1,"timeRestore":false,"kibanaSavedObjectMeta":{"searchSourceJSON":"{\"filter\":[{\"query\":{\"query_string\":{\"analyze_wildcard\":true,\"query\":\"*\"}}}]}"}}